Workbook
Name Scenario: Inputs!$B$1
Name Scenario_Index: Inputs!$B$2
Name Eff_Duplicates: Inputs!$E$5
Name Eff_Duplicates_Worst: Inputs!$B$5
Name Eff_Duplicates_Base: Inputs!$C$5
Name Eff_Duplicates_Best: Inputs!$D$5
Name Eff_PayToTerms: Inputs!$E$6
Name Eff_PayToTerms_Worst: Inputs!$B$6
Name Eff_PayToTerms_Base: Inputs!$C$6
Name Eff_PayToTerms_Best: Inputs!$D$6
Name Eff_Approval: Inputs!$E$7
Name Eff_Approval_Worst: Inputs!$B$7
Name Eff_Approval_Base: Inputs!$C$7
Name Eff_Approval_Best: Inputs!$D$7
Name Eff_EntryValidation: Inputs!$E$8
Name Eff_EntryValidation_Worst: Inputs!$B$8
Name Eff_EntryValidation_Base: Inputs!$C$8
Name Eff_EntryValidation_Best: Inputs!$D$8
Name Eff_POCompliance: Inputs!$E$9
Name Eff_POCompliance_Worst: Inputs!$B$9
Name Eff_POCompliance_Base: Inputs!$C$9
Name Eff_POCompliance_Best: Inputs!$D$9
Name Recovery_Rate: Inputs!$E$10
Name Recovery_Rate_Worst: Inputs!$B$10
Name Recovery_Rate_Base: Inputs!$C$10
Name Recovery_Rate_Best: Inputs!$D$10
Name PO_Premium: Inputs!$E$11
Name PO_Premium_Worst: Inputs!$B$11
Name PO_Premium_Base: Inputs!$C$11
Name PO_Premium_Best: Inputs!$D$11
Name Cost_Multiplier: Inputs!$E$12
Name Cost_Multiplier_Worst: Inputs!$B$12
Name Cost_Multiplier_Base: Inputs!$C$12
Name Cost_Multiplier_Best: Inputs!$D$12
Name CoC: Inputs!$E$13
Name CoC_Worst: Inputs!$B$13
Name CoC_Base: Inputs!$C$13
Name CoC_Best: Inputs!$D$13
Name Ramp_Y1: Inputs!$E$14
Name Ramp_Y1_Worst: Inputs!$B$14
Name Ramp_Y1_Base: Inputs!$C$14
Name Ramp_Y1_Best: Inputs!$D$14
Name M_Duplicates: Inputs!$B$17
Name M_PaymentRun: Inputs!$B$18
Name M_SlowApproval: Inputs!$B$19
Name M_Rework: Inputs!$B$20
Name M_PaidDuplicates: Inputs!$B$21
Name M_NoPOSpend: Inputs!$B$22
Name M_WorkingCapital: Inputs!$B$23
Name M_CoC_Measure: Inputs!$B$24
Name Rate_IT: Inputs!$B$27
Name Rate_Internal: Inputs!$B$28
Name Hard_Benefit: Levers!$E$11
Name Estimated_Saving: Levers!$E$12
Name Investment: Levers!$E$13
Name Investment_Estimate: Levers!$E$14
Name Run_Cost: Levers!$E$15
Name Run_Cost_Estimate: Levers!$E$16
Name Hard_NPV: 'Cash flow'!$B$11
Name Hard_ROI: 'Cash flow'!$B$12

Sheet README
A1: AP Spend Leakage Analyzer: business case model (Rheinwerk Komponenten GmbH, fictional client)
A2: Generated by scripts/build_excel_workbook.py from the same figures as the app. All data is synthetic.
A4: How to use
A5: 1. Inputs: pick Worst, Base or Best in the yellow cell, or change any blue value.
A6: 2. Levers, Cash flow and Scenarios recalculate: NPV, ROI and payback are formulas, not pasted values.
A7: 3. Sensitivity moves one assumption at a time to its worst and best value (tornado chart).
A8: 4. Checks compares the workbook with the Python model; every row shows OK in the Base scenario.
A10: Colour code
A11: Blue text: input or assumption you may change. Black: formula. Green: link to another sheet.
A12: Yellow fill: the scenario switch.
A14: Rules kept from the analysis
A15: Hard benefits (cash) and estimated savings are never added into one headline: the NPV is shown for both.
... A18: Pivot tables and Power Query: see bi/excel/README.md (built in Excel from bi/data/*.csv).

Sheet Inputs
A1: Scenario | B1: Base | C1: Worst, Base or Best: drives the Active column below
A2: Scenario index | B2: =MATCH(Scenario,{"Worst","Base","Best"},0)
A4: Assumption | B4: Worst | C4: Base | D4: Best | E4: Active | F4: Name | G4: Source
A5: Duplicates prevented | B5: 0.8 | C5: 0.95795869 | D5: 1 | E5: =INDEX(B5:D5,Scenario_Index) | F5: Eff_Duplicates | G5: Data: € share of duplicates that reused a PO
A6: Pay-to-terms effectiveness | B6: 0.6 | C6: 0.8 | D6: 1 | E6: =INDEX(B6:D6,Scenario_Index) | F6: Eff_PayToTerms | G6: Consultant estimate; depends on run frequency
A7: Late approvals avoided | B7: 0.25 | C7: 0.5 | D7: 0.75 | E7: =INDEX(B7:D7,Scenario_Index) | F7: Eff_Approval | G7: Consultant estimate; confirm with budget owners
A8: Rework prevented at entry | B8: 0.3 | C8: 0.55156951 | D8: 0.7 | E8: =INDEX(B8:D8,Scenario_Index) | F8: Eff_EntryValidation | G8: Data: share of rejections preventable at entry
A9: No-PO spend brought under PO | B9: 0.25 | C9: 0.53703704 | D9: 0.75 | E9: =INDEX(B9:D9,Scenario_Index) | F9: Eff_POCompliance | G9: Data: gap closed by the 90% PO-compliance target
A10: Paid duplicates recovered | B10: 0.6 | C10: 0.8 | D10: 0.95 | E10: =INDEX(B10:D10,Scenario_Index) | F10: Recovery_Rate | G10: Open question Q1 (CFO, AP Manager)
A11: Premium paid without a PO | B11: 0.02 | C11: 0.05 | D11: 0.08 | E11: =INDEX(B11:D11,Scenario_Index) | F11: PO_Premium | G11: Assumption in Measure; confirm with Procurement
A12: Implementation and running cost | B12: 1.5 | C12: 1 | D12: 0.9 | E12: =INDEX(B12:D12,Scenario_Index) | F12: Cost_Multiplier | G12: Consultant estimate; IT overruns are common
A13: Cost of capital (discount rate) | B13: 0.1 | C13: 0.08 | D13: 0.06 | E13: =INDEX(B13:D13,Scenario_Index) | F13: CoC | G13: Open question Q3 (CFO)
A14: Year-1 benefit realised | B14: 0.5 | C14: 0.75 | D14: 0.9 | E14: =INDEX(B14:D14,Scenario_Index) | F14: Ramp_Y1 | G14: Go-live in the first quarter (charter goal date)
A16: Measured figure (12 months to 31 Aug 2026) | B16: € a year | F16: Name | G16: Source
A17: Duplicate payments (no duplicate check at entry) | B17: 60264.78 | F17: M_Duplicates | G17: src/root_cause.py, leakage by cause
A18: Payment run ignores discount and due dates | B18: 6278.47 | F18: M_PaymentRun | G18: src/root_cause.py, leakage by cause
A19: Slow approval, no rework | B19: 4018.31 | F19: M_SlowApproval | G19: src/root_cause.py, leakage by cause
A20: Rework delays approval past the deadline | B20: 2991.31 | F20: M_Rework | G20: src/root_cause.py, leakage by cause
A21: Duplicates already paid (one-off claim-back base) | B21: 60264.78 | F21: M_PaidDuplicates | G21: src/impact.py, duplicate copies already paid
A22: Spend without a purchase order | B22: 797772.6 | F22: M_NoPOSpend | G22: src/kpis.py, no-PO invoice spend
A23: Working capital given away, at the Measure cost of capital | B23: 12531.63 | F23: M_WorkingCapital | G23: src/impact.py, early-payment cost
A24: Cost of capital used in Measure | B24: 0.08 | F24: M_CoC_Measure | G24: src/impact.py; working capital € scales with the Active cost of capital
A26: Cost rate | B26: € a day | F26: Name | G26: Source
A27: IT day rate (external SAP consultant) | B27: 1000 | F27: Rate_IT | G27: Consultant estimate; confirm with IT
A28: Internal day rate (AP or Procurement staff, fully loaded) | B28: 400 | F28: Rate_Internal | G28: About €50 an hour; confirm with HR controlling

Sheet Levers
A1: Fix | B1: Benefit type | C1: € a year at stake | D1: Removed | E1: € benefit a year | F1: IT days | G1: Business days | H1: One-off cost at estimate | I1: One-off cost | J1: Run days a year | K1: Running cost a year | L1: Owner
A2: Block duplicates at invoice entry | B2: Hard benefit | C2: =M_Duplicates | D2: =Eff_Duplicates | E2: =C2*D2 | F2: 8 | G2: 3 | H2: =F2*Rate_IT+G2*Rate_Internal | I2: =H2*Cost_Multiplier | J2: 4 | K2: =J2*Rate_Internal*Cost_Multiplier | L2: AP Manager, IT
A3: Pay to terms | B3: Hard benefit | C3: =M_PaymentRun | D3: =Eff_PayToTerms | E3: =C3*D3 | F3: 5 | G3: 3 | H3: =F3*Rate_IT+G3*Rate_Internal | I3: =H3*Cost_Multiplier | J3: 0 | K3: =J3*Rate_Internal*Cost_Multiplier | L3: AP Manager (Treasury consulted)
A4: Approval deadline for discount invoices | B4: Hard benefit | C4: =M_SlowApproval | D4: =Eff_Approval | E4: =C4*D4 | F4: 10 | G4: 5 | H4: =F4*Rate_IT+G4*Rate_Internal | I4: =H4*Cost_Multiplier | J4: 2 | K4: =J4*Rate_Internal*Cost_Multiplier | L4: Budget owners, AP Manager
A5: Validate cost centre and PO at entry | B5: Hard benefit | C5: =M_Rework | D5: =Eff_EntryValidation | E5: =C5*D5 | F5: 12 | G5: 3 | H5: =F5*Rate_IT+G5*Rate_Internal | I5: =H5*Cost_Multiplier | J5: 0 | K5: =J5*Rate_Internal*Cost_Multiplier | L5: IT, AP clerks
A6: No PO, no pay | B6: Estimated saving | C6: =M_NoPOSpend*PO_Premium | D6: =Eff_POCompliance | E6: =C6*D6 | F6: 3 | G6: 20 | H6: =F6*Rate_IT+G6*Rate_Internal | I6: =H6*Cost_Multiplier | J6: 15 | K6: =J6*Rate_Internal*Cost_Multiplier | L6: Procurement lead
A7: Pay to terms: working capital | B7: Estimated saving | C7: =M_WorkingCapital*CoC/M_CoC_Measure | D7: =Eff_PayToTerms | E7: =C7*D7 | F7: 0 | G7: 0 | H7: =F7*Rate_IT+G7*Rate_Internal | I7: =H7*Cost_Multiplier | J7: 0 | K7: =J7*Rate_Internal*Cost_Multiplier | L7: AP Manager (Treasury consulted)
A8: Payment block without approval | B8: Control only | C8: 0 | D8: 0 | E8: =C8*D8 | F8: 2 | G8: 1 | H8: =F8*Rate_IT+G8*Rate_Internal | I8: =H8*Cost_Multiplier | J8: 0 | K8: =J8*Rate_Internal*Cost_Multiplier | L8: AP Manager, Internal Audit
A9: Programme management and training | B9: Control only | C9: 0 | D9: 0 | E9: =C9*D9 | F9: 0 | G9: 15 | H9: =F9*Rate_IT+G9*Rate_Internal | I9: =H9*Cost_Multiplier | J9: 0 | K9: =J9*Rate_Internal*Cost_Multiplier | L9: AP Manager
A11: Hard benefit a year | E11: =SUMIF(B2:B9,"Hard benefit",E2:E9)
A12: Estimated saving a year | E12: =SUMIF(B2:B9,"Estimated saving",E2:E9)
A13: One-off investment | E13: =SUM(I2:I9)
A14: One-off investment at estimate | E14: =SUM(H2:H9)
A15: Running cost a year | E15: =SUM(K2:K9)
A16: Running cost a year at estimate | E16: =SUMPRODUCT(J2:J9)*Rate_Internal

Sheet Cash flow
A1: Hard benefits only (the headline)
A2: € | B2: Year 0 | C2: Year 1 | D2: Year 2 | E2: Year 3
A3: Benefit | B3: =0 | C3: =Hard_Benefit*Ramp_Y1 | D3: =Hard_Benefit | E3: =Hard_Benefit
A4: Duplicates recovered (one-off) | B4: =0 | C4: =M_PaidDuplicates*Recovery_Rate | D4: =0 | E4: =0
A5: Cost | B5: =-Investment | C5: =-Run_Cost | D5: =-Run_Cost | E5: =-Run_Cost
A6: Net cash flow | B6: =SUM(B3:B5) | C6: =SUM(C3:C5) | D6: =SUM(D3:D5) | E6: =SUM(E3:E5)
A7: Discount factor | B7: =1/(1+CoC)^0 | C7: =1/(1+CoC)^1 | D7: =1/(1+CoC)^2 | E7: =1/(1+CoC)^3
A8: Discounted | B8: =B6*B7 | C8: =C6*C7 | D8: =D6*D7 | E8: =E6*E7
A9: Running total | B9: =B6 | C9: =B9+C6 | D9: =C9+D6 | E9: =D9+E6
A11: NPV (3 years) | B11: =SUM(B8:E8)
A12: ROI (3 years) | B12: =(SUM(C6:E6)+B6)/-B6
A13: Payback (months) | B13: =IF(C9>=0,-B9/C6*12,IF(D9>=0,12-C9/D6*12,IF(E9>=0,24-D9/E6*12,"Not within 3 years")))
A15: Including estimated savings (never the headline)
A16: € | B16: Year 0 | C16: Year 1 | D16: Year 2 | E16: Year 3
A17: Benefit | B17: =0 | C17: =(Hard_Benefit+Estimated_Saving)*Ramp_Y1 | D17: =(Hard_Benefit+Estimated_Saving) | E17: =(Hard_Benefit+Estimated_Saving)
A18: Duplicates recovered (one-off) | B18: =0 | C18: =M_PaidDuplicates*Recovery_Rate | D18: =0 | E18: =0
A19: Cost | B19: =-Investment | C19: =-Run_Cost | D19: =-Run_Cost | E19: =-Run_Cost
A20: Net cash flow | B20: =SUM(B17:B19) | C20: =SUM(C17:C19) | D20: =SUM(D17:D19) | E20: =SUM(E17:E19)
A21: Discount factor | B21: =1/(1+CoC)^0 | C21: =1/(1+CoC)^1 | D21: =1/(1+CoC)^2 | E21: =1/(1+CoC)^3
A22: Discounted | B22: =B20*B21 | C22: =C20*C21 | D22: =D20*D21 | E22: =E20*E21
A23: Running total | B23: =B20 | C23: =B23+C20 | D23: =C23+D20 | E23: =D23+E20
A25: NPV (3 years) | B25: =SUM(B22:E22)
A26: ROI (3 years) | B26: =(SUM(C20:E20)+B20)/-B20
A27: Payback (months) | B27: =IF(C23>=0,-B23/C20*12,IF(D23>=0,12-C23/D20*12,IF(E23>=0,24-D23/E20*12,"Not within 3 years")))

Sheet Scenarios
A1: € | B1: Worst | C1: Base | D1: Best
A2: Hard benefit a year | B2: =M_Duplicates*Eff_Duplicates_Worst+M_PaymentRun*Eff_PayToTerms_Worst+M_SlowApproval*Eff_Approval_Worst+M_Rework*Eff_EntryValidation_Worst | C2: =M_Duplicates*Eff_Duplicates_Base+M_PaymentRun*Eff_PayToTerms_Base+M_SlowApproval*Eff_Approval_Base+M_Rework*Eff_EntryValidation_Base | D2: =M_Duplicates*Eff_Duplicates_Best+M_PaymentRun*Eff_PayToTerms_Best+M_SlowApproval*Eff_Approval_Best+M_Rework*Eff_EntryValidation_Best
A3: Estimated saving a year | B3: =M_NoPOSpend*PO_Premium_Worst*Eff_POCompliance_Worst+M_WorkingCapital*CoC_Worst/M_CoC_Measure*Eff_PayToTerms_Worst | C3: =M_NoPOSpend*PO_Premium_Base*Eff_POCompliance_Base+M_WorkingCapital*CoC_Base/M_CoC_Measure*Eff_PayToTerms_Base | D3: =M_NoPOSpend*PO_Premium_Best*Eff_POCompliance_Best+M_WorkingCapital*CoC_Best/M_CoC_Measure*Eff_PayToTerms_Best
A4: Investment | B4: =Investment_Estimate*Cost_Multiplier_Worst | C4: =Investment_Estimate*Cost_Multiplier_Base | D4: =Investment_Estimate*Cost_Multiplier_Best
A5: Running cost a year | B5: =Run_Cost_Estimate*Cost_Multiplier_Worst | C5: =Run_Cost_Estimate*Cost_Multiplier_Base | D5: =Run_Cost_Estimate*Cost_Multiplier_Best
A6: Net cash flow, year 1 | B6: =B2*Ramp_Y1_Worst+M_PaidDuplicates*Recovery_Rate_Worst-B5 | C6: =C2*Ramp_Y1_Base+M_PaidDuplicates*Recovery_Rate_Base-C5 | D6: =D2*Ramp_Y1_Best+M_PaidDuplicates*Recovery_Rate_Best-D5
A7: Net cash flow, years 2 and 3 | B7: =B2-B5 | C7: =C2-C5 | D7: =D2-D5
A8: NPV, hard benefits | B8: =-B4+B6/(1+CoC_Worst)+B7*(1/(1+CoC_Worst)^2+1/(1+CoC_Worst)^3) | C8: =-C4+C6/(1+CoC_Base)+C7*(1/(1+CoC_Base)^2+1/(1+CoC_Base)^3) | D8: =-D4+D6/(1+CoC_Best)+D7*(1/(1+CoC_Best)^2+1/(1+CoC_Best)^3)
A9: ROI, hard benefits | B9: =(B6+2*B7-B4)/B4 | C9: =(C6+2*C7-C4)/C4 | D9: =(D6+2*D7-D4)/D4
A10: Payback (months) | B10: =IF(B6>=B4,B4/B6*12,12+(B4-B6)/B7*12) | C10: =IF(C6>=C4,C4/C6*12,12+(C4-C6)/C7*12) | D10: =IF(D6>=D4,D4/D6*12,12+(D4-D6)/D7*12)
A11: NPV without the one-off claim-back | B11: =B8-M_PaidDuplicates*Recovery_Rate_Worst/(1+CoC_Worst) | C11: =C8-M_PaidDuplicates*Recovery_Rate_Base/(1+CoC_Base) | D11: =D8-M_PaidDuplicates*Recovery_Rate_Best/(1+CoC_Best)
A12: NPV including estimated savings | B12: =B8+B3*(Ramp_Y1_Worst/(1+CoC_Worst)+1/(1+CoC_Worst)^2+1/(1+CoC_Worst)^3) | C12: =C8+C3*(Ramp_Y1_Base/(1+CoC_Base)+1/(1+CoC_Base)^2+1/(1+CoC_Base)^3) | D12: =D8+D3*(Ramp_Y1_Best/(1+CoC_Best)+1/(1+CoC_Best)^2+1/(1+CoC_Best)^3)
A14: Payback assumes it falls within years 1–2, as in every case here; the Cash flow sheet computes it year by year.

Sheet Sensitivity
A1: Assumption | B1: Set to | C1: Duplicates prevented | D1: Pay-to-terms effectiveness | E1: Late approvals avoided | F1: Rework prevented at entry | G1: Paid duplicates recovered | H1: Implementation and running cost | I1: Cost of capital (discount rate) | J1: Year-1 benefit realised | K1: Hard benefit | L1: Investment | M1: Running cost | N1: Year 1 net | O1: Years 2–3 net | P1: NPV, hard benefits
A2: Implementation and running cost | B2: Worst | C2: =Eff_Duplicates_Base | D2: =Eff_PayToTerms_Base | E2: =Eff_Approval_Base | F2: =Eff_EntryValidation_Base | G2: =Recovery_Rate_Base | H2: =Cost_Multiplier_Worst | I2: =CoC_Base | J2: =Ramp_Y1_Base | K2: =M_Duplicates*C2+M_PaymentRun*D2+M_SlowApproval*E2+M_Rework*F2 | L2: =Investment_Estimate*H2 | M2: =Run_Cost_Estimate*H2 | N2: =K2*J2+M_PaidDuplicates*G2-M2 | O2: =K2-M2 | P2: =-L2+N2/(1+I2)+O2*(1/(1+I2)^2+1/(1+I2)^3)
A3: Implementation and running cost | B3: Best | C3: =Eff_Duplicates_Base | D3: =Eff_PayToTerms_Base | E3: =Eff_Approval_Base | F3: =Eff_EntryValidation_Base | G3: =Recovery_Rate_Base | H3: =Cost_Multiplier_Best | I3: =CoC_Base | J3: =Ramp_Y1_Base | K3: =M_Duplicates*C3+M_PaymentRun*D3+M_SlowApproval*E3+M_Rework*F3 | L3: =Investment_Estimate*H3 | M3: =Run_Cost_Estimate*H3 | N3: =K3*J3+M_PaidDuplicates*G3-M3 | O3: =K3-M3 | P3: =-L3+N3/(1+I3)+O3*(1/(1+I3)^2+1/(1+I3)^3)
A4: Duplicates prevented | B4: Worst | C4: =Eff_Duplicates_Worst | D4: =Eff_PayToTerms_Base | E4: =Eff_Approval_Base | F4: =Eff_EntryValidation_Base | G4: =Recovery_Rate_Base | H4: =Cost_Multiplier_Base | I4: =CoC_Base | J4: =Ramp_Y1_Base | K4: =M_Duplicates*C4+M_PaymentRun*D4+M_SlowApproval*E4+M_Rework*F4 | L4: =Investment_Estimate*H4 | M4: =Run_Cost_Estimate*H4 | N4: =K4*J4+M_PaidDuplicates*G4-M4 | O4: =K4-M4 | P4: =-L4+N4/(1+I4)+O4*(1/(1+I4)^2+1/(1+I4)^3)
A5: Duplicates prevented | B5: Best | C5: =Eff_Duplicates_Best | D5: =Eff_PayToTerms_Base | E5: =Eff_Approval_Base | F5: =Eff_EntryValidation_Base | G5: =Recovery_Rate_Base | H5: =Cost_Multiplier_Base | I5: =CoC_Base | J5: =Ramp_Y1_Base | K5: =M_Duplicates*C5+M_PaymentRun*D5+M_SlowApproval*E5+M_Rework*F5 | L5: =Investment_Estimate*H5 | M5: =Run_Cost_Estimate*H5 | N5: =K5*J5+M_PaidDuplicates*G5-M5 | O5: =K5-M5 | P5: =-L5+N5/(1+I5)+O5*(1/(1+I5)^2+1/(1+I5)^3)
A6: Year-1 benefit realised | B6: Worst | C6: =Eff_Duplicates_Base | D6: =Eff_PayToTerms_Base | E6: =Eff_Approval_Base | F6: =Eff_EntryValidation_Base | G6: =Recovery_Rate_Base | H6: =Cost_Multiplier_Base | I6: =CoC_Base | J6: =Ramp_Y1_Worst | K6: =M_Duplicates*C6+M_PaymentRun*D6+M_SlowApproval*E6+M_Rework*F6 | L6: =Investment_Estimate*H6 | M6: =Run_Cost_Estimate*H6 | N6: =K6*J6+M_PaidDuplicates*G6-M6 | O6: =K6-M6 | P6: =-L6+N6/(1+I6)+O6*(1/(1+I6)^2+1/(1+I6)^3)
A7: Year-1 benefit realised | B7: Best | C7: =Eff_Duplicates_Base | D7: =Eff_PayToTerms_Base | E7: =Eff_Approval_Base | F7: =Eff_EntryValidation_Base | G7: =Recovery_Rate_Base | H7: =Cost_Multiplier_Base | I7: =CoC_Base | J7: =Ramp_Y1_Best | K7: =M_Duplicates*C7+M_PaymentRun*D7+M_SlowApproval*E7+M_Rework*F7 | L7: =Investment_Estimate*H7 | M7: =Run_Cost_Estimate*H7 | N7: =K7*J7+M_PaidDuplicates*G7-M7 | O7: =K7-M7 | P7: =-L7+N7/(1+I7)+O7*(1/(1+I7)^2+1/(1+I7)^3)
A8: Paid duplicates recovered | B8: Worst | C8: =Eff_Duplicates_Base | D8: =Eff_PayToTerms_Base | E8: =Eff_Approval_Base | F8: =Eff_EntryValidation_Base | G8: =Recovery_Rate_Worst | H8: =Cost_Multiplier_Base | I8: =CoC_Base | J8: =Ramp_Y1_Base | K8: =M_Duplicates*C8+M_PaymentRun*D8+M_SlowApproval*E8+M_Rework*F8 | L8: =Investment_Estimate*H8 | M8: =Run_Cost_Estimate*H8 | N8: =K8*J8+M_PaidDuplicates*G8-M8 | O8: =K8-M8 | P8: =-L8+N8/(1+I8)+O8*(1/(1+I8)^2+1/(1+I8)^3)
A9: Paid duplicates recovered | B9: Best | C9: =Eff_Duplicates_Base | D9: =Eff_PayToTerms_Base | E9: =Eff_Approval_Base | F9: =Eff_EntryValidation_Base | G9: =Recovery_Rate_Best | H9: =Cost_Multiplier_Base | I9: =CoC_Base | J9: =Ramp_Y1_Base | K9: =M_Duplicates*C9+M_PaymentRun*D9+M_SlowApproval*E9+M_Rework*F9 | L9: =Investment_Estimate*H9 | M9: =Run_Cost_Estimate*H9 | N9: =K9*J9+M_PaidDuplicates*G9-M9 | O9: =K9-M9 | P9: =-L9+N9/(1+I9)+O9*(1/(1+I9)^2+1/(1+I9)^3)
A10: Cost of capital (discount rate) | B10: Worst | C10: =Eff_Duplicates_Base | D10: =Eff_PayToTerms_Base | E10: =Eff_Approval_Base | F10: =Eff_EntryValidation_Base | G10: =Recovery_Rate_Base | H10: =Cost_Multiplier_Base | I10: =CoC_Worst | J10: =Ramp_Y1_Base | K10: =M_Duplicates*C10+M_PaymentRun*D10+M_SlowApproval*E10+M_Rework*F10 | L10: =Investment_Estimate*H10 | M10: =Run_Cost_Estimate*H10 | N10: =K10*J10+M_PaidDuplicates*G10-M10 | O10: =K10-M10 | P10: =-L10+N10/(1+I10)+O10*(1/(1+I10)^2+1/(1+I10)^3)
A11: Cost of capital (discount rate) | B11: Best | C11: =Eff_Duplicates_Base | D11: =Eff_PayToTerms_Base | E11: =Eff_Approval_Base | F11: =Eff_EntryValidation_Base | G11: =Recovery_Rate_Base | H11: =Cost_Multiplier_Base | I11: =CoC_Best | J11: =Ramp_Y1_Base | K11: =M_Duplicates*C11+M_PaymentRun*D11+M_SlowApproval*E11+M_Rework*F11 | L11: =Investment_Estimate*H11 | M11: =Run_Cost_Estimate*H11 | N11: =K11*J11+M_PaidDuplicates*G11-M11 | O11: =K11-M11 | P11: =-L11+N11/(1+I11)+O11*(1/(1+I11)^2+1/(1+I11)^3)
A12: Pay-to-terms effectiveness | B12: Worst | C12: =Eff_Duplicates_Base | D12: =Eff_PayToTerms_Worst | E12: =Eff_Approval_Base | F12: =Eff_EntryValidation_Base | G12: =Recovery_Rate_Base | H12: =Cost_Multiplier_Base | I12: =CoC_Base | J12: =Ramp_Y1_Base | K12: =M_Duplicates*C12+M_PaymentRun*D12+M_SlowApproval*E12+M_Rework*F12 | L12: =Investment_Estimate*H12 | M12: =Run_Cost_Estimate*H12 | N12: =K12*J12+M_PaidDuplicates*G12-M12 | O12: =K12-M12 | P12: =-L12+N12/(1+I12)+O12*(1/(1+I12)^2+1/(1+I12)^3)
A13: Pay-to-terms effectiveness | B13: Best | C13: =Eff_Duplicates_Base | D13: =Eff_PayToTerms_Best | E13: =Eff_Approval_Base | F13: =Eff_EntryValidation_Base | G13: =Recovery_Rate_Base | H13: =Cost_Multiplier_Base | I13: =CoC_Base | J13: =Ramp_Y1_Base | K13: =M_Duplicates*C13+M_PaymentRun*D13+M_SlowApproval*E13+M_Rework*F13 | L13: =Investment_Estimate*H13 | M13: =Run_Cost_Estimate*H13 | N13: =K13*J13+M_PaidDuplicates*G13-M13 | O13: =K13-M13 | P13: =-L13+N13/(1+I13)+O13*(1/(1+I13)^2+1/(1+I13)^3)
A14: Late approvals avoided | B14: Worst | C14: =Eff_Duplicates_Base | D14: =Eff_PayToTerms_Base | E14: =Eff_Approval_Worst | F14: =Eff_EntryValidation_Base | G14: =Recovery_Rate_Base | H14: =Cost_Multiplier_Base | I14: =CoC_Base | J14: =Ramp_Y1_Base | K14: =M_Duplicates*C14+M_PaymentRun*D14+M_SlowApproval*E14+M_Rework*F14 | L14: =Investment_Estimate*H14 | M14: =Run_Cost_Estimate*H14 | N14: =K14*J14+M_PaidDuplicates*G14-M14 | O14: =K14-M14 | P14: =-L14+N14/(1+I14)+O14*(1/(1+I14)^2+1/(1+I14)^3)
A15: Late approvals avoided | B15: Best | C15: =Eff_Duplicates_Base | D15: =Eff_PayToTerms_Base | E15: =Eff_Approval_Best | F15: =Eff_EntryValidation_Base | G15: =Recovery_Rate_Base | H15: =Cost_Multiplier_Base | I15: =CoC_Base | J15: =Ramp_Y1_Base | K15: =M_Duplicates*C15+M_PaymentRun*D15+M_SlowApproval*E15+M_Rework*F15 | L15: =Investment_Estimate*H15 | M15: =Run_Cost_Estimate*H15 | N15: =K15*J15+M_PaidDuplicates*G15-M15 | O15: =K15-M15 | P15: =-L15+N15/(1+I15)+O15*(1/(1+I15)^2+1/(1+I15)^3)
A16: Rework prevented at entry | B16: Worst | C16: =Eff_Duplicates_Base | D16: =Eff_PayToTerms_Base | E16: =Eff_Approval_Base | F16: =Eff_EntryValidation_Worst | G16: =Recovery_Rate_Base | H16: =Cost_Multiplier_Base | I16: =CoC_Base | J16: =Ramp_Y1_Base | K16: =M_Duplicates*C16+M_PaymentRun*D16+M_SlowApproval*E16+M_Rework*F16 | L16: =Investment_Estimate*H16 | M16: =Run_Cost_Estimate*H16 | N16: =K16*J16+M_PaidDuplicates*G16-M16 | O16: =K16-M16 | P16: =-L16+N16/(1+I16)+O16*(1/(1+I16)^2+1/(1+I16)^3)
A17: Rework prevented at entry | B17: Best | C17: =Eff_Duplicates_Base | D17: =Eff_PayToTerms_Base | E17: =Eff_Approval_Base | F17: =Eff_EntryValidation_Best | G17: =Recovery_Rate_Base | H17: =Cost_Multiplier_Base | I17: =CoC_Base | J17: =Ramp_Y1_Base | K17: =M_Duplicates*C17+M_PaymentRun*D17+M_SlowApproval*E17+M_Rework*F17 | L17: =Investment_Estimate*H17 | M17: =Run_Cost_Estimate*H17 | N17: =K17*J17+M_PaidDuplicates*G17-M17 | O17: =K17-M17 | P17: =-L17+N17/(1+I17)+O17*(1/(1+I17)^2+1/(1+I17)^3)
A19: Tornado: NPV with one assumption at its worst and best value
A20: Assumption | B20: NPV at worst | C20: NPV at best | D20: Swing
A21: Implementation and running cost | B21: =P2 | C21: =P3 | D21: =ABS(C21-B21)
A22: Duplicates prevented | B22: =P4 | C22: =P5 | D22: =ABS(C22-B22)
A23: Year-1 benefit realised | B23: =P6 | C23: =P7 | D23: =ABS(C23-B23)
A24: Paid duplicates recovered | B24: =P8 | C24: =P9 | D24: =ABS(C24-B24)
A25: Cost of capital (discount rate) | B25: =P10 | C25: =P11 | D25: =ABS(C25-B25)
A26: Pay-to-terms effectiveness | B26: =P12 | C26: =P13 | D26: =ABS(C26-B26)
A27: Late approvals avoided | B27: =P14 | C27: =P15 | D27: =ABS(C27-B27)
A28: Rework prevented at entry | B28: =P16 | C28: =P17 | D28: =ABS(C28-B28)

Sheet Checks
A1: Figure | B1: Workbook | C1: Python model | D1: Difference | E1: Status
A2: Hard benefit a year | B2: =Hard_Benefit | C2: 66413.02 | D2: =B2-C2 | E2: =IF(Scenario<>"Base","Switch Inputs to Base",IF(ABS(D2)<=0.5,"OK","CHECK"))
A3: Estimated saving a year | B3: =Estimated_Saving | C3: 31446.98 | D3: =B3-C3 | E3: =IF(Scenario<>"Base","Switch Inputs to Base",IF(ABS(D3)<=0.5,"OK","CHECK"))
A4: One-off investment | B4: =Investment | C4: 60000 | D4: =B4-C4 | E4: =IF(Scenario<>"Base","Switch Inputs to Base",IF(ABS(D4)<=0.5,"OK","CHECK"))
A5: Running cost a year | B5: =Run_Cost | C5: 8400 | D5: =B5-C5 | E5: =IF(Scenario<>"Base","Switch Inputs to Base",IF(ABS(D5)<=0.5,"OK","CHECK"))
A6: NPV, hard benefits | B6: =Hard_NPV | C6: 118772.36 | D6: =B6-C6 | E6: =IF(Scenario<>"Base","Switch Inputs to Base",IF(ABS(D6)<=0.5,"OK","CHECK"))
A7: ROI, hard benefits (%) | B7: =Hard_ROI*100 | C7: 242.7 | D7: =B7-C7 | E7: =IF(Scenario<>"Base","Switch Inputs to Base",IF(ABS(D7)<=0.5,"OK","CHECK"))
A8: Payback, hard benefits (months) | B8: =Hard_Payback | C8: 8 | D8: =B8-C8 | E8: =IF(Scenario<>"Base","Switch Inputs to Base",IF(ABS(D8)<=0.5,"OK","CHECK"))
A9: NPV including estimated savings | B9: =WithEstimated_NPV | C9: 192534.88 | D9: =B9-C9 | E9: =IF(Scenario<>"Base","Switch Inputs to Base",IF(ABS(D9)<=0.5,"OK","CHECK"))
A10: Worst case: NPV, hard benefits | B10: =Scenarios!B8 | C10: 21039.82 | D10: =B10-C10 | E10: =IF(ABS(D10)<=0.5,"OK","CHECK")
A11: Worst case: NPV without claim-back | B11: =Scenarios!B11 | C11: -11831.88 | D11: =B11-C11 | E11: =IF(ABS(D11)<=0.5,"OK","CHECK")
A12: Worst case: NPV including estimated savings | B12: =Scenarios!B12 | C12: 48247.5 | D12: =B12-C12 | E12: =IF(ABS(D12)<=0.5,"OK","CHECK")
A13: Base case: NPV, hard benefits | B13: =Scenarios!C8 | C13: 118772.36 | D13: =B13-C13 | E13: =IF(ABS(D13)<=0.5,"OK","CHECK")
A14: Base case: NPV without claim-back | B14: =Scenarios!C11 | C14: 74131.79 | D14: =B14-C14 | E14: =IF(ABS(D14)<=0.5,"OK","CHECK")
A15: Base case: NPV including estimated savings | B15: =Scenarios!C12 | C15: 192534.88 | D15: =B15-C15 | E15: =IF(ABS(D15)<=0.5,"OK","CHECK")
A16: Best case: NPV, hard benefits | B16: =Scenarios!D8 | C16: 164567.11 | D16: =B16-C16 | E16: =IF(ABS(D16)<=0.5,"OK","CHECK")
A17: Best case: NPV without claim-back | B17: =Scenarios!D11 | C17: 110556.22 | D17: =B17-C17 | E17: =IF(ABS(D17)<=0.5,"OK","CHECK")
A18: Best case: NPV including estimated savings | B18: =Scenarios!D12 | C18: 312234.98 | D18: =B18-C18 | E18: =IF(ABS(D18)<=0.5,"OK","CHECK")
A19: Tornado: Implementation and running cost at worst | B19: =Sensitivity!B21 | C19: 77948.56 | D19: =B19-C19 | E19: =IF(ABS(D19)<=0.5,"OK","CHECK")
A20: Tornado: Implementation and running cost at best | B20: =Sensitivity!C21 | C20: 126937.13 | D20: =B20-C20 | E20: =IF(ABS(D20)<=0.5,"OK","CHECK")
A21: Tornado: Duplicates prevented at worst | B21: =Sensitivity!B22 | C21: 96443.64 | D21: =B21-C21 | E21: =IF(ABS(D21)<=0.5,"OK","CHECK")
A22: Tornado: Duplicates prevented at best | B22: =Sensitivity!C22 | C22: 124715.24 | D22: =B22-C22 | E22: =IF(ABS(D22)<=0.5,"OK","CHECK")
A23: Tornado: Year-1 benefit realised at worst | B23: =Sensitivity!B23 | C23: 103398.98 | D23: =B23-C23 | E23: =IF(ABS(D23)<=0.5,"OK","CHECK")
A24: Tornado: Year-1 benefit realised at best | B24: =Sensitivity!C23 | C24: 127996.39 | D24: =B24-C24 | E24: =IF(ABS(D24)<=0.5,"OK","CHECK")
A25: Tornado: Paid duplicates recovered at worst | B25: =Sensitivity!B24 | C25: 107612.22 | D25: =B25-C25 | E25: =IF(ABS(D25)<=0.5,"OK","CHECK")
A26: Tornado: Paid duplicates recovered at best | B26: =Sensitivity!C24 | C26: 127142.47 | D26: =B26-C26 | E26: =IF(ABS(D26)<=0.5,"OK","CHECK")
A27: Tornado: Cost of capital (discount rate) at worst | B27: =Sensitivity!B25 | C27: 113004.85 | D27: =B27-C27 | E27: =IF(ABS(D27)<=0.5,"OK","CHECK")
A28: Tornado: Cost of capital (discount rate) at best | B28: =Sensitivity!C25 | C28: 124888.89 | D28: =B28-C28 | E28: =IF(ABS(D28)<=0.5,"OK","CHECK")
A29: Tornado: Pay-to-terms effectiveness at worst | B29: =Sensitivity!B26 | C29: 115826.99 | D29: =B29-C29 | E29: =IF(ABS(D29)<=0.5,"OK","CHECK")
A30: Tornado: Pay-to-terms effectiveness at best | B30: =Sensitivity!C26 | C30: 121717.74 | D30: =B30-C30 | E30: =IF(ABS(D30)<=0.5,"OK","CHECK")
A31: Tornado: Late approvals avoided at worst | B31: =Sensitivity!B27 | C31: 116416.01 | D31: =B31-C31 | E31: =IF(ABS(D31)<=0.5,"OK","CHECK")
A32: Tornado: Late approvals avoided at best | B32: =Sensitivity!C27 | C32: 121128.72 | D32: =B32-C32 | E32: =IF(ABS(D32)<=0.5,"OK","CHECK")
A33: Tornado: Rework prevented at entry at worst | B33: =Sensitivity!B28 | C33: 117007.24 | D33: =B33-C33 | E33: =IF(ABS(D33)<=0.5,"OK","CHECK")
A34: Tornado: Rework prevented at entry at best | B34: =Sensitivity!C28 | C34: 119813.82 | D34: =B34-C34 | E34: =IF(ABS(D34)<=0.5,"OK","CHECK")
A36: All checks | E36: =IF(COUNTIF(E2:E34,"OK")=33,"ALL OK","SEE ABOVE")
